audio_shot_detection/__init__.py
audio_shot_detection/audio_shot_detection_script.py
audio_shot_detection/config.py
audio_shot_detection/detector 2.py
audio_shot_detection/detector.py
audio_shot_detection/directory_convention_funcs.py
ww_audio_shot_detection/__init__.py
ww_audio_shot_detection/audio_shot_detection_script.py
ww_audio_shot_detection/config.py
ww_audio_shot_detection/detector 2.py
ww_audio_shot_detection/detector.py
ww_audio_shot_detection/directory_convention_funcs.py
ww_audio_shot_detection/utils/__init__.py
ww_audio_shot_detection/utils/annotation_file_manager.py
ww_audio_shot_detection/utils/annotator.py
ww_audio_shot_detection/utils/audio_shot_annotator.py
ww_audio_shot_detection/utils/common_utils.py
ww_audio_shot_detection/utils/dynamo_db.py
ww_audio_shot_detection/utils/hoop_annotator.py
ww_audio_shot_detection/utils/rectangle.py
ww_audio_shot_detection/utils/shot_annotator.py
ww_audio_shot_detection/utils/vids_downloader.py
ww_audio_shot_detection-0.0.4.dist-info/METADATA
ww_audio_shot_detection-0.0.4.dist-info/WHEEL
ww_audio_shot_detection-0.0.4.dist-info/top_level.txt
ww_audio_shot_detection-0.0.4.dist-info/RECORD
