Metadata-Version: 2.1
Name: ww-audio-shot-detection
Version: 0.0.4
Summary: Package to detect shots
Home-page: https://github.com/wingwarp/BallTracking
Author: wingwarp
Requires-Dist: requests
Requires-Dist: matplotlib
Requires-Dist: pandas
Requires-Dist: boto3
Requires-Dist: m3u8
Requires-Dist: aiohttp
Requires-Dist: imutils
